ffast/__init__.py
ffast/preprocessor.py
ffast/poincare/__init__.py
ffast/poincare/poincare.txt
ffast/poincare/token.py
ffast/poincare/tokeniser.py
ffast/poincare/tokens.py
ffast/poincare/utils.py
ffast/wordnet/__init__.py
ffast/wordnet/token.py
ffast/wordnet/tokeniser.py
ffast/wordnet/tokens.py
ffast/wordnet/utils.py
ffast/wordnet/nltk_data/corpora/omw-1.4.zip
ffast/wordnet/nltk_data/corpora/stopwords.zip
ffast/wordnet/nltk_data/corpora/wordnet.zip
ffast-0.4.10.dist-info/METADATA
ffast-0.4.10.dist-info/WHEEL
ffast-0.4.10.dist-info/top_level.txt
ffast-0.4.10.dist-info/RECORD
