Metadata-Version: 2.1
Name: ffast
Version: 0.4.10
Summary: FFAST: Fast Fourier Analysis for Sentence embeddings and Tokenisation
Home-page: UNKNOWN
Author: Mohammed Terry-Jack
Author-email: <mohammedterryjack@gmail.com>
License: UNKNOWN
Keywords: python,embedding,tokenisation,fast fourier,nlp,nlu,poincare,wordnet,lite,fast,sentence encoder
Platform: UNKNOWN
Classifier: Development Status :: 4 - Beta
Classifier: Intended Audience :: Developers
Classifier: Programming Language :: Python :: 3
Classifier: Operating System :: MacOS :: MacOS X
Requires-Dist: nltk
Requires-Dist: jellyfish
Requires-Dist: Unidecode
Requires-Dist: numpy
Requires-Dist: scipy
